amogus.py
sus_amogus-0.1.1.dist-info/LICENSE
sus_amogus-0.1.1.dist-info/METADATA
sus_amogus-0.1.1.dist-info/WHEEL
sus_amogus-0.1.1.dist-info/top_level.txt
sus_amogus-0.1.1.dist-info/RECORD
