Metadata-Version: 2.1
Name: sus-amogus
Version: 0.1.1
Summary: sus
Home-page: https://github.com/HugeBrain16/amogus
Author: HugeBrain16
Author-email: joshtuck373@gmail.com
License: MIT
Platform: UNKNOWN
